<mapping>
	<XMLtoEDD>
		<map>
			<setattribute tag='BPumpID' RAttribute='BPumpID' enclosure='job' type='integer' subtype=''/>
			<setattribute tag='BrandID' RAttribute='BrandID' enclosure='job' type='integer' subtype=''/>
			<setattribute tag='currentdate' RAttribute='currentdate' enclosure='job' type='date' subtype=''/>
			<setattribute tag='motivator' RAttribute='motivator' enclosure='job' type='string' subtype=''/>
			<setattribute tag='result' RAttribute='result' enclosure='job' type='integer' subtype=''/>
			
			<setattribute tag='ACPowerAdaptor' RAttribute='ACPowerAdaptor' enclosure='breastpump' type='string' subtype=''/>
			<setattribute tag='AdjustableSpeed' RAttribute='AdjustableSpeed' enclosure='breastpump' type='string' subtype=''/>
			<setattribute tag='AdjustableSuction' RAttribute='AdjustableSuction' enclosure='breastpump' type='string' subtype=''/>
			<setattribute tag='BPumpID' RAttribute='BPumpID' enclosure='breastpump' type='integer' subtype=''/>
			<setattribute tag='BrandID' RAttribute='BrandID' enclosure='breastpump' type='integer' subtype=''/>
			<setattribute tag='BreastShieldType' RAttribute='BreastShieldType' enclosure='breastpump' type='string' subtype=''/>
			<setattribute tag='CarAdaptor' RAttribute='CarAdaptor' enclosure='breastpump' type='string' subtype=''/>
			<setattribute tag='ErgonomicHandle' RAttribute='ErgonomicHandle' enclosure='breastpump' type='string' subtype=''/>
			<setattribute tag='HandsFreeOption' RAttribute='HandsFreeOption' enclosure='breastpump' type='string' subtype=''/>
			<setattribute tag='LCDDisplay' RAttribute='LCDDisplay' enclosure='breastpump' type='string' subtype=''/>
			<setattribute tag='MemoryFeature' RAttribute='MemoryFeature' enclosure='breastpump' type='string' subtype=''/>
			<setattribute tag='motivatorTotal' RAttribute='motivatorTotal' enclosure='breastpump' type='double' subtype=''/>
			<setattribute tag='MultiPhaseExpression' RAttribute='MultiPhaseExpression' enclosure='breastpump' type='string' subtype=''/>
			<setattribute tag='OneTouchLetDownButton' RAttribute='OneTouchLetDownButton' enclosure='breastpump' type='string' subtype=''/>
			<setattribute tag='PumpingTimer' RAttribute='PumpingTimer' enclosure='breastpump' type='string' subtype=''/>
			<setattribute tag='Type' RAttribute='Type' enclosure='breastpump' type='string' subtype=''/>

			<createentity entity='breastpump' tag='breastpump' id='id'/>
			<createentity entity='constants' tag='constants' id='id'/>
			<createentity entity='job' tag='job' id='id'/>
		</map>

		<entities>
			<entity name='breastpump' number='*'/>
			<entity name='constants' number='1'/>
			<entity name='job' number='1'/>
		</entities>

		<initialization>
			<initialentity entity='job' epush='true'/>
			<initialentity entity='constants' epush='true'/>
		</initialization>
	</XMLtoEDD>
</mapping>

